fetchable/__init__.py
fetchable/__version__.py
fetchable/configuration.py
fetchable/fetchable.py
fetchable-0.1.5.dist-info/LICENSE
fetchable-0.1.5.dist-info/METADATA
fetchable-0.1.5.dist-info/WHEEL
fetchable-0.1.5.dist-info/top_level.txt
fetchable-0.1.5.dist-info/RECORD
