Metadata-Version: 2.1
Name: fetchable
Version: 0.1.5
Summary: Client SDK for Fetchable
Home-page: UNKNOWN
Author: Fetchable
Author-email: support@fetchable.ai
License: Apache License 2.0
Project-URL: Issue tracker, https://github.com/fetchableai/fetchable-python/issues
Project-URL: Source, https://github.com/fetchableai/fetchable-python
Project-URL: Company, https://fetchable.ai
Platform: UNKNOWN
Classifier: Development Status :: 3 - Alpha
Classifier: Intended Audience :: Developers
Classifier: Natural Language :: English
Classifier: License :: OSI Approved :: Apache Software License
Classifier: Programming Language :: Python
Classifier: Programming Language :: Python :: 2.7
Classifier: Programming Language :: Python :: 3.6
Classifier: Topic :: Scientific/Engineering :: Artificial Intelligence
Classifier: Topic :: Software Development :: Libraries 
